LICENSE
MANIFEST.in
README
setup.py
drm4g/__init__.py
drm4g/__main__.py
drm4g/_static_version.py
drm4g/_version.py
drm4g.egg-info/PKG-INFO
drm4g.egg-info/SOURCES.txt
drm4g.egg-info/dependency_links.txt
drm4g.egg-info/entry_points.txt
drm4g.egg-info/requires.txt
drm4g.egg-info/top_level.txt
drm4g/api/__init__.py
drm4g/commands/__init__.py
drm4g/commands/clear.py
drm4g/commands/conf.py
drm4g/commands/docopt.py
drm4g/commands/host.py
drm4g/commands/id.py
drm4g/commands/job.py
drm4g/commands/main.py
drm4g/commands/resource.py
drm4g/commands/restart.py
drm4g/commands/start.py
drm4g/commands/status.py
drm4g/commands/stop.py
drm4g/communicators/__init__.py
drm4g/communicators/local.py
drm4g/communicators/openssh.py
drm4g/communicators/openssh_wrapper.py
drm4g/communicators/ssh.py
drm4g/communicators/ssh_fabric.py
drm4g/conf/cloud_config.conf
drm4g/conf/cloudsetup.json
drm4g/conf/gw_drm4g_wrapper.sh
drm4g/conf/gw_original_monitor.sh
drm4g/conf/gw_original_wrapper.sh
drm4g/conf/gwd.conf
drm4g/conf/job_template.default
drm4g/conf/logger.conf
drm4g/conf/resources.conf
drm4g/conf/resources_default.conf
drm4g/conf/resources_ssh.conf
drm4g/conf/sched.conf
drm4g/conf/wrf4g_wrapper.sh
drm4g/core/__init__.py
drm4g/core/configure.py
drm4g/core/em_mad.py
drm4g/core/im_mad.py
drm4g/core/tm_mad.py
drm4g/managers/__init__.py
drm4g/managers/cream.py
drm4g/managers/fork.py
drm4g/managers/loadleveler.py
drm4g/managers/lsf.py
drm4g/managers/marenostrum.py
drm4g/managers/neptuno.py
drm4g/managers/pbs.py
drm4g/managers/pbs_custom.py
drm4g/managers/sge.py
drm4g/managers/slurm.py
drm4g/managers/slurm_res.py
drm4g/managers/rocci/__init__.py
drm4g/managers/rocci/rocci.py
drm4g/managers/rocci/utils.py
drm4g/utils/__init__.py
drm4g/utils/command.py
drm4g/utils/dynamic.py
drm4g/utils/list.py
drm4g/utils/logger.py
drm4g/utils/message.py
drm4g/utils/rsl2.py
drm4g/utils/url.py
drm4g/utils/importlib/__init__.py
extras/README
extras/drm4g_autocomplete.sh
extras/devel/vagrant/Centos72/VagrantFile
extras/devel/vagrant/Centos72/linux.sh
extras/examples/test_api.py
gridway-5.8/LICENSE
gridway-5.8/Makefile.am
gridway-5.8/Makefile.in
gridway-5.8/NOTICE
gridway-5.8/README
